LICENSE
README.md
setup.py
./husteblume/__init__.py
./husteblume/api.py
./husteblume/user.py
husteblume/__init__.py
husteblume/api.py
husteblume/user.py
husteblume.egg-info/PKG-INFO
husteblume.egg-info/SOURCES.txt
husteblume.egg-info/dependency_links.txt
husteblume.egg-info/requires.txt
husteblume.egg-info/top_level.txt