Metadata-Version: 2.1
Name: husteblume
Version: 0.0.4
Summary: Library to access the TK.de Husteblume API
Home-page: https://github.com/SharkyRawr/pyHusteblume
Author: Sophie Luna Schumann
Author-email: pypi@sophie.lgbt
License: UNKNOWN
Project-URL: Bug Tracker, https://github.com/SharkyRawr/pyHusteblume/issues
Platform: UNKNOWN
Classifier: Programming Language :: Python :: 3
Classifier: License :: OSI Approved :: MIT License
Classifier: Operating System :: OS Independent
Requires-Python: >=3.6
License-File: LICENSE
